README
plivohelper.py
setup.py
plivohelper.egg-info/PKG-INFO
plivohelper.egg-info/SOURCES.txt
plivohelper.egg-info/dependency_links.txt
plivohelper.egg-info/top_level.txt