Metadata-Version: 1.0
Name: plivohelper
Version: 0.3.5
Summary: Plivo API client and RESTXML generator
Home-page: https://github.com/plivo/plivohelper-python
Author: Plivo Team
Author-email: hello@plivo.org
License: UNKNOWN
Keywords: plivo,rest
Platform: UNKNOWN
Classifier: Programming Language :: Python
Classifier: Operating System :: OS Independent
Classifier: License :: OSI Approved :: MIT License
Classifier: Intended Audience :: Developers
Classifier: Development Status :: 5 - Production/Stable
Classifier: Topic :: Software Development :: Libraries :: Python Modules
Classifier: Topic :: Communications :: Telephony
